setup.py
test_distribution/Binomialdistribution.py
test_distribution/Gaussiandistribution.py
test_distribution/Generaldistribution.py
test_distribution/__init__.py
test_distribution.egg-info/PKG-INFO
test_distribution.egg-info/SOURCES.txt
test_distribution.egg-info/dependency_links.txt
test_distribution.egg-info/not-zip-safe
test_distribution.egg-info/top_level.txt